axirunner/__init__.py
axirunner/_version.py
axirunner/axirunner.py
axirunner/conf/configspec.conf
axirunner/conf/sources.conf
axirunner/conf/stations.conf
axirunner/conf/velocity.nd
axirunner/configobj/__init__.py
axirunner/configobj/_version.py
axirunner/configobj/validate.py
axirunner-0.2.dist-info/LICENSE.txt
axirunner-0.2.dist-info/METADATA
axirunner-0.2.dist-info/WHEEL
axirunner-0.2.dist-info/entry_points.txt
axirunner-0.2.dist-info/top_level.txt
axirunner-0.2.dist-info/RECORD
