Metadata-Version: 2.1
Name: axirunner
Version: 0.2
Summary: Make synthetic seismograms using Axitra. The easy way™.
Home-page: http://www.ipgp.fr/~satriano
Author: Claudio Satriano
Author-email: satriano@ipgp.fr
License: CeCILL Free Software License Agreement, Version 2.1
Platform: OS Independent
Classifier: Development Status :: 2 - Pre-Alpha
Classifier: Environment :: Console
Classifier: Intended Audience :: Science/Research
Classifier: License :: OSI Approved :: CEA CNRS Inria Logiciel Libre License, version 2.1 (CeCILL-2.1)
Classifier: Operating System :: OS Independent
Classifier: Programming Language :: Python
Classifier: Programming Language :: Python :: 3
Classifier: Programming Language :: Python :: 3.7
Classifier: Programming Language :: Python :: 3.8
Classifier: Topic :: Scientific/Engineering
Classifier: Topic :: Scientific/Engineering :: Physics
Requires-Python: >3
Requires-Dist: obspy (>=1.2.0)
Requires-Dist: scipy (>=0.17)
Requires-Dist: proj
